py_playlist/__init__.py
py_playlist/__main__.py
py_playlist/cli.py
py_playlist/config.py
py_playlist/logs.py
py_playlist/main.py
py_playlist/playlist.py
py_playlist/utils.py
py_playlist/tests/__init__.py
py_playlist/tests/test_cli.py
py_playlist/tests/test_config.py
py_playlist/tests/test_logs.py
py_playlist/tests/test_utils.py
py_playlist-0.0.3.dist-info/LICENSE
py_playlist-0.0.3.dist-info/METADATA
py_playlist-0.0.3.dist-info/WHEEL
py_playlist-0.0.3.dist-info/entry_points.txt
py_playlist-0.0.3.dist-info/top_level.txt
py_playlist-0.0.3.dist-info/RECORD
