Metadata-Version: 2.1
Name: py-playlist
Version: 0.0.3
Summary: A playlist manager for terminal based players
Home-page: https://github.com/gustavospiess/py-playlist
Author: Gustavo Henrique Spiess
Author-email: gustavospiess@gmail.com
License: UNKNOWN
Platform: UNKNOWN
Classifier: Programming Language :: Python :: 3
Classifier: License :: OSI Approved :: MIT License
Classifier: Operating System :: OS Independent
Requires-Python: >=3.6
Requires-Dist: click (>=7.1.2)
Requires-Dist: click-aliases (>=1.0.1)
